pykorm/__init__.py
pykorm/exceptions.py
pykorm/fields.py
pykorm/meta.py
pykorm/models.py
pykorm/pykorm.py
pykorm/query.py
pykorm-0.60.0.dist-info/LICENCE
pykorm-0.60.0.dist-info/METADATA
pykorm-0.60.0.dist-info/WHEEL
pykorm-0.60.0.dist-info/top_level.txt
pykorm-0.60.0.dist-info/RECORD
