Metadata-Version: 2.1
Name: pykorm
Version: 0.60.0
Summary: Pykorm: a dead simple Kubernetes ORM
Home-page: https://github.com/Frankkkkk/pykorm
Author: Frank Villaro-Dixon - Infomaniak Network SA
Author-email: frank.villaro@infomaniak.com
License: GNU General Public License v3 (GPLv3)
Classifier: Development Status :: 4 - Beta
Classifier: Environment :: Console
Classifier: Intended Audience :: Developers
Classifier: License :: OSI Approved :: GNU General Public License v3 (GPLv3)
Classifier: Operating System :: POSIX :: Linux
Classifier: Programming Language :: Python :: 3.6
Classifier: Programming Language :: Python :: Implementation :: PyPy
Classifier: Topic :: Software Development :: Libraries :: Python Modules
Requires-Python: >=3.6
License-File: LICENCE
Requires-Dist: kubernetes (>=11.0)
Requires-Dist: dpath (==2.0.1)
